qiskit/aqua/VERSION.txt
qiskit/aqua/__init__.py
qiskit/aqua/_logging.py
qiskit/aqua/aqua_error.py
qiskit/aqua/aqua_globals.py
qiskit/aqua/deprecation.py
qiskit/aqua/missing_optional_library_error.py
qiskit/aqua/quantum_instance.py
qiskit/aqua/version.py
qiskit/aqua/algorithms/__init__.py
qiskit/aqua/algorithms/algorithm_result.py
qiskit/aqua/algorithms/classical_algorithm.py
qiskit/aqua/algorithms/quantum_algorithm.py
qiskit/aqua/algorithms/vq_algorithm.py
qiskit/aqua/algorithms/amplitude_amplifiers/__init__.py
qiskit/aqua/algorithms/amplitude_amplifiers/grover.py
qiskit/aqua/algorithms/amplitude_estimators/__init__.py
qiskit/aqua/algorithms/amplitude_estimators/ae.py
qiskit/aqua/algorithms/amplitude_estimators/ae_algorithm.py
qiskit/aqua/algorithms/amplitude_estimators/ae_utils.py
qiskit/aqua/algorithms/amplitude_estimators/iqae.py
qiskit/aqua/algorithms/amplitude_estimators/mlae.py
qiskit/aqua/algorithms/amplitude_estimators/q_factory.py
qiskit/aqua/algorithms/amplitude_estimators/s_0_reflection.py
qiskit/aqua/algorithms/amplitude_estimators/s_psi_0_reflection.py
qiskit/aqua/algorithms/classifiers/__init__.py
qiskit/aqua/algorithms/classifiers/vqc.py
qiskit/aqua/algorithms/classifiers/qsvm/__init__.py
qiskit/aqua/algorithms/classifiers/qsvm/_qsvm_abc.py
qiskit/aqua/algorithms/classifiers/qsvm/_qsvm_binary.py
qiskit/aqua/algorithms/classifiers/qsvm/_qsvm_estimator.py
qiskit/aqua/algorithms/classifiers/qsvm/_qsvm_multiclass.py
qiskit/aqua/algorithms/classifiers/qsvm/qsvm.py
qiskit/aqua/algorithms/classifiers/sklearn_svm/__init__.py
qiskit/aqua/algorithms/classifiers/sklearn_svm/_rbf_svc_estimator.py
qiskit/aqua/algorithms/classifiers/sklearn_svm/_sklearn_svm_abc.py
qiskit/aqua/algorithms/classifiers/sklearn_svm/_sklearn_svm_binary.py
qiskit/aqua/algorithms/classifiers/sklearn_svm/_sklearn_svm_multiclass.py
qiskit/aqua/algorithms/classifiers/sklearn_svm/sklearn_svm.py
qiskit/aqua/algorithms/distribution_learners/__init__.py
qiskit_aqua-0.9.5.dist-info/LICENSE.txt
qiskit_aqua-0.9.5.dist-info/METADATA
qiskit_aqua-0.9.5.dist-info/WHEEL
qiskit_aqua-0.9.5.dist-info/top_level.txt
qiskit_aqua-0.9.5.dist-info/RECORD
