Metadata-Version: 2.1
Name: qiskit-aqua
Version: 0.9.5
Summary: Qiskit Aqua: An extensible library of quantum computing algorithms
Home-page: https://github.com/Qiskit/qiskit-aqua
Author: Qiskit Aqua Development Team
Author-email: hello@qiskit.org
License: Apache-2.0
Keywords: qiskit sdk quantum aqua
Platform: UNKNOWN
Classifier: Environment :: Console
Classifier: License :: OSI Approved :: Apache Software License
Classifier: Intended Audience :: Developers
Classifier: Intended Audience :: Science/Research
Classifier: Operating System :: Microsoft :: Windows
Classifier: Operating System :: MacOS
Classifier: Operating System :: POSIX :: Linux
Classifier: Programming Language :: Python :: 3 :: Only
Classifier: Programming Language :: Python :: 3.6
Classifier: Programming Language :: Python :: 3.7
Classifier: Programming Language :: Python :: 3.8
Classifier: Programming Language :: Python :: 3.9
Classifier: Topic :: Scientific/Engineering
Requires-Python: >=3.6
Provides-Extra: torch
Provides-Extra: cplex
Provides-Extra: cvx
Provides-Extra: pyscf
Provides-Extra: skquant
License-File: LICENSE.txt
